makeprojects/__init__.py
makeprojects/__main__.py
makeprojects/build_objects.py
makeprojects/build_rules.py
makeprojects/buildme.py
makeprojects/cleanme.py
makeprojects/codeblocks.py
makeprojects/codewarrior.py
makeprojects/config.py
makeprojects/core.py
makeprojects/defaults.py
makeprojects/doxygen.py
makeprojects/enums.py
makeprojects/glsl_support.py
makeprojects/hlsl_support.py
makeprojects/makefile.py
makeprojects/makerez.py
makeprojects/masm_support.py
makeprojects/modules.py
makeprojects/ninja.py
makeprojects/python.py
makeprojects/rebuildme.py
makeprojects/slicer.py
makeprojects/util.py
makeprojects/validators.py
makeprojects/visual_studio.py
makeprojects/visual_studio_2010.py
makeprojects/visual_studio_utils.py
makeprojects/watcom.py
makeprojects/watcom_util.py
makeprojects/xcode.py
makeprojects/xcode_utils.py
makeprojects-1.1.0.dist-info/LICENSE.txt
makeprojects-1.1.0.dist-info/METADATA
makeprojects-1.1.0.dist-info/WHEEL
makeprojects-1.1.0.dist-info/entry_points.txt
makeprojects-1.1.0.dist-info/top_level.txt
makeprojects-1.1.0.dist-info/RECORD
