Metadata-Version: 2.1
Name: makeprojects
Version: 1.1.0
Summary: IDE project generator for Visual Studio, XCode, etc...
Home-page: http://makeprojects.readthedocs.io
Author: Rebecca Ann Heineman <becky@burgerbecky.com>
Author-email: becky@burgerbecky.com
License: MIT License
Keywords: burger,perforce,burgerlib,development,makeprojects,xcode,visual studio,visualstudio,codeblocks,watcom,ps3,ps4,ps5,xboxone,xbox360,vita,mac,macosx,ios,android,stadia,nintendo,switch
Platform: Any
Classifier: Development Status :: 5 - Production/Stable
Classifier: Environment :: Console
Classifier: Intended Audience :: Developers
Classifier: Topic :: Software Development
Classifier: Topic :: Software Development :: Build Tools
Classifier: License :: OSI Approved :: MIT License
Classifier: Operating System :: OS Independent
Classifier: Natural Language :: English
Classifier: Programming Language :: Python
Classifier: Programming Language :: Python :: 2
Classifier: Programming Language :: Python :: 2.7
Classifier: Programming Language :: Python :: 3
Classifier: Programming Language :: Python :: 3.4
Classifier: Programming Language :: Python :: 3.5
Classifier: Programming Language :: Python :: 3.6
Classifier: Programming Language :: Python :: 3.7
Classifier: Programming Language :: Python :: 3.8
Classifier: Programming Language :: Python :: 3.9
Classifier: Programming Language :: Python :: 3.10
Classifier: Programming Language :: Python :: 3.11
Classifier: Programming Language :: Python :: 3.12
Requires-Python: >=2.7,!=3.0.*,!=3.1.*,!=3.2.*,!=3.3.*
License-File: LICENSE.txt
Requires-Dist: setuptools>=17.1
Requires-Dist: enum34>=1.0.0
Requires-Dist: burger>=1.3.1
Requires-Dist: argparse>=1.0
Requires-Dist: glob2>=0.6
